<?xml version="1.0" encoding="utf-8"?>
<Window>
	<Form Height="535" Id="MSTZ100FM" Left="8" OnLoadCompleted="onLoadCompleted" PidAttrib="7" Title="MSTZ100FM" TooltipFont="Default,0" Top="8" Ver="1.0" Width="1062" WorkArea="true">
		<Datasets>
			<Dataset DataSetType="Dataset" Id="Dataset0">
				<Contents>
					<colinfo id="cd" size="256" type="STRING"/>
					<colinfo id="cdnm" size="256" type="STRING"/>
					<record>
						<cd></cd>
						<cdnm>선택</cdnm>
					</record>
					<record>
						<cd>C1</cd>
						<cdnm>C1</cdnm>
					</record>
					<record>
						<cd>E1</cd>
						<cdnm>E1</cdnm>
					</record>
					<record>
						<cd>H1</cd>
						<cdnm>H1</cdnm>
					</record>
					<record>
						<cd>S1</cd>
						<cdnm>S1</cdnm>
					</record>
				</Contents>
			</Dataset>
			<Dataset DataSetType="Dataset" Id="Dataset2">
				<Contents>
					<colinfo id="cd" size="256" type="STRING"/>
					<colinfo id="cdnm" size="256" type="STRING"/>
					<record>
						<cd></cd>
						<cdnm>선택</cdnm>
					</record>
					<record>
						<cd>A</cd>
						<cdnm>A</cdnm>
					</record>
					<record>
						<cd>C</cd>
						<cdnm>C</cdnm>
					</record>
					<record>
						<cd>D</cd>
						<cdnm>D</cdnm>
					</record>
					<record>
						<cd>Q</cd>
						<cdnm>Q</cdnm>
					</record>
				</Contents>
			</Dataset>
			<Dataset DataSetType="Dataset" Id="ds_list">
				<Contents>
					<colinfo id="col1" size="256" type="STRING"/>
					<colinfo id="col2" size="256" type="STRING"/>
					<colinfo id="col3" size="256" type="STRING"/>
					<colinfo id="col4" size="256" type="STRING"/>
					<colinfo id="col5" size="256" type="STRING"/>
					<colinfo id="col6" size="256" type="STRING"/>
					<colinfo id="col7" size="256" type="STRING"/>
					<colinfo id="col8" size="256" type="STRING"/>
					<colinfo id="col9" size="256" type="STRING"/>
					<colinfo id="col10" size="256" type="STRING"/>
					<colinfo id="col11" size="256" type="STRING"/>
					<colinfo id="col12" size="256" type="STRING"/>
					<colinfo id="code" size="256" type="STRING"/>
					<colinfo id="col13" size="256" type="STRING"/>
					<record>
						<code>1100</code>
						<col1>HMC(ULSAN)</col1>
						<col10>22112370</col10>
						<col11></col11>
						<col12></col12>
						<col13>19331795</col13>
						<col2>3844292</col2>
						<col3>4325108</col3>
						<col4>5432425</col4>
						<col5>5691680</col5>
						<col6>7036020</col6>
						<col7>6336110</col7>
						<col8>6914265</col8>
						<col9>9085379</col9>
					</record>
					<record>
						<code>1100</code>
						<col1>HMC(ULSAN)</col1>
						<col10></col10>
						<col11></col11>
						<col12></col12>
						<col13></col13>
						<col2>4903446</col2>
						<col3></col3>
						<col4></col4>
						<col5></col5>
						<col6></col6>
						<col7></col7>
						<col8></col8>
						<col9></col9>
					</record>
					<record>
						<code>1110</code>
						<col1>KMC(KJ)</col1>
						<col10>4248242</col10>
						<col11></col11>
						<col12></col12>
						<col13>3792597</col13>
						<col2>1036770</col2>
						<col3>1137361</col3>
						<col4>1291684</col4>
						<col5>1339437</col5>
						<col6>134266</col6>
						<col7>1238612</col7>
						<col8>1085236</col8>
						<col9>1338781</col9>
					</record>
					<record>
						<code>1110</code>
						<col1>KMC(KJ)</col1>
						<col10></col10>
						<col11></col11>
						<col12></col12>
						<col13></col13>
						<col2>938608</col2>
						<col3></col3>
						<col4></col4>
						<col5></col5>
						<col6></col6>
						<col7></col7>
						<col8></col8>
						<col9></col9>
					</record>
				</Contents>
			</Dataset>
			<Dataset DataSetType="Dataset" Id="ds_list2">
				<Contents>
					<colinfo id="cd" size="256" type="STRING"/>
					<colinfo id="cdnm" size="256" type="STRING"/>
					<record>
						<cd>16</cd>
						<cdnm>현장지원</cdnm>
					</record>
					<record>
						<cd></cd>
						<cdnm></cdnm>
					</record>
					<record>
						<cd></cd>
						<cdnm></cdnm>
					</record>
					<record>
						<cd></cd>
						<cdnm></cdnm>
					</record>
					<record>
						<cd></cd>
						<cdnm></cdnm>
					</record>
					<record>
						<cd></cd>
						<cdnm></cdnm>
					</record>
					<record>
						<cd></cd>
						<cdnm></cdnm>
					</record>
					<record>
						<cd></cd>
						<cdnm></cdnm>
					</record>
					<record>
						<cd></cd>
						<cdnm></cdnm>
					</record>
					<record>
						<cd></cd>
						<cdnm></cdnm>
					</record>
					<record>
						<cd></cd>
						<cdnm></cdnm>
					</record>
					<record>
						<cd></cd>
						<cdnm></cdnm>
					</record>
					<record>
						<cd></cd>
						<cdnm></cdnm>
					</record>
					<record>
						<cd></cd>
						<cdnm></cdnm>
					</record>
					<record>
						<cd></cd>
						<cdnm></cdnm>
					</record>
				</Contents>
			</Dataset>
			<Dataset DataSetType="Dataset" Id="ds_list3">
				<Contents>
					<colinfo id="cd" size="256" type="STRING"/>
					<colinfo id="cdnm" size="256" type="STRING"/>
					<record>
						<cd></cd>
						<cdnm></cdnm>
					</record>
					<record>
						<cd></cd>
						<cdnm></cdnm>
					</record>
					<record>
						<cd></cd>
						<cdnm></cdnm>
					</record>
					<record>
						<cd></cd>
						<cdnm></cdnm>
					</record>
					<record>
						<cd></cd>
						<cdnm></cdnm>
					</record>
					<record>
						<cd></cd>
						<cdnm></cdnm>
					</record>
					<record>
						<cd></cd>
						<cdnm></cdnm>
					</record>
					<record>
						<cd></cd>
						<cdnm></cdnm>
					</record>
					<record>
						<cd></cd>
						<cdnm></cdnm>
					</record>
					<record>
						<cd></cd>
						<cdnm></cdnm>
					</record>
					<record>
						<cd></cd>
						<cdnm></cdnm>
					</record>
					<record>
						<cd></cd>
						<cdnm></cdnm>
					</record>
					<record>
						<cd></cd>
						<cdnm></cdnm>
					</record>
					<record>
						<cd></cd>
						<cdnm></cdnm>
					</record>
				</Contents>
			</Dataset>
			<Dataset DataSetType="Dataset" Id="ds_buso">
				<Contents>
					<colinfo id="cd" size="256" type="STRING"/>
					<colinfo id="cdnm" size="256" type="STRING"/>
					<record>
						<cd>3012</cd>
						<cdnm>施設班</cdnm>
					</record>
					<record>
						<cd>3023</cd>
						<cdnm>營業班</cdnm>
					</record>
					<record>
						<cd>3031</cd>
						<cdnm>改善班</cdnm>
					</record>
					<record>
						<cd>3033</cd>
						<cdnm>工場內物洗班</cdnm>
					</record>
					<record>
						<cd>3036</cd>
						<cdnm>ST&#32;組立班</cdnm>
					</record>
					<record>
						<cd>3038</cd>
						<cdnm>ST&#32;組立&#32;2&#32;班</cdnm>
					</record>
					<record>
						<cd>3049</cd>
						<cdnm>AL&#32;組立班</cdnm>
					</record>
					<record>
						<cd>3040</cd>
						<cdnm>AL&#32;SUB&#32;班</cdnm>
					</record>
					<record>
						<cd>3041</cd>
						<cdnm>WM&#32;工作班</cdnm>
					</record>
					<record>
						<cd>3042</cd>
						<cdnm>PW&#32;AR2&#32;班</cdnm>
					</record>
					<record>
						<cd>3045</cd>
						<cdnm>WM&#32;組立&#32;1&#32;班</cdnm>
					</record>
					<record>
						<cd>3046</cd>
						<cdnm>RWM&#32;班</cdnm>
					</record>
					<record>
						<cd>3047</cd>
						<cdnm>WM&#32;AR&#32;班</cdnm>
					</record>
					<record>
						<cd>3049</cd>
						<cdnm>PWM&#32;組立&#32;1&#32;班</cdnm>
					</record>
					<record>
						<cd>3051</cd>
						<cdnm>PW&#32;AR&#32;班</cdnm>
					</record>
				</Contents>
			</Dataset>
		</Datasets>
		<Static BKColor="white" Border="Flat" BorderColor="#b4b4b4" Height="25" Id="Static4" Left="-1" TabOrder="7" Top="32" Width="1060"></Static>
		<Static BKColor="#dfdfdf" Border="Flat" BorderColor="#b4b4b4" Height="25" Id="Static6" Left="263" TabOrder="6" Top="32" Width="106"></Static>
		<Static Border="None" Color="#333333" Font="굴림,9,Bold" Height="16" Id="Static5" Left="285" Style="static" TabOrder="2" Text="PlantCD" Top="37" VAlign="Middle" Width="69"></Static>
		<Static BKColor="#dfdfdf" Border="Flat" BorderColor="#b4b4b4" Height="25" Id="Static1" Left="-1" TabOrder="5" Top="32" Width="106"></Static>
		<Shape BKColor="#888888" Bottom="47" Height="5" Id="Shape3" Left="275" LineColor="#dceaf7" Right="280" TabOrder="1" Top="42" Type="Ellipse" Width="5"></Shape>
		<Shape BKColor="#888888" Bottom="46" Height="5" Id="Shape1" Left="11" LineColor="#dceaf7" Right="16" TabOrder="3" Top="41" Type="Ellipse" Width="5"></Shape>
		<Static Border="None" Color="#333333" Font="굴림,9,Bold" Height="16" Id="Static21" Left="21" Style="static" TabOrder="4" Text="사업부" Top="37" VAlign="Middle" Width="69"></Static>
		<Combo Border="Flat" BorderColor="SCROLLBAR" CodeColumn="cd" Color="#333333" DataColumn="cdnm" Height="21" Id="Combo0" INDEX="0" InnerDataset="ds_buso" Left="106" ResetIndex="FIRST" TabOrder="8" Top="33" Width="156"></Combo>
		<Grid AutoEnter="TRUE" BindDataset="ds_list" BkColor2="default" BoldHead="true" Border="Flat" BorderColor="#b4b4b4" Bottom="517" Editable="TRUE" Enable="true" EndLineColor="default" FillArea="TRUE" HeadBorder="Flat" HeadHeight="25" Height="432" Id="Grid0" InputPanel="FALSE" LineColor="#b4b4b4" Right="1060" TabOrder="9" TabStop="true" Top="85" UseDBuff="true" UsePopupMenu="true" UseSelColor="FALSE" Visible="true" VLineColor="#b4b4b4" WheelScrollRow="1" Width="1060">
			<contents>
				<format id="Default">
					<columns>
						<col width="58"/>
						<col width="97"/>
						<col width="60"/>
						<col width="60"/>
						<col width="60"/>
						<col width="60"/>
						<col width="60"/>
						<col width="60"/>
						<col width="60"/>
						<col width="60"/>
						<col width="60"/>
						<col width="60"/>
						<col width="60"/>
						<col width="60"/>
						<col width="60"/>
					</columns>
					<head>
						<cell bkcolor="#dfdfdf" col="0" color="#002043" display="text" text="코드"/>
						<cell bkcolor="#dfdfdf" col="1" color="#002043" display="text" text="거래선명"/>
						<cell bkcolor="#dfdfdf" col="2" color="#002043" display="text" text="2010/08"/>
						<cell bkcolor="#dfdfdf" col="3" color="#002043" display="text" text="2010/09"/>
						<cell bkcolor="#dfdfdf" col="4" color="#002043" display="text" text="2010/10"/>
						<cell bkcolor="#dfdfdf" col="5" color="#002043" display="text" text="2010/11"/>
						<cell bkcolor="#dfdfdf" col="6" color="#002043" display="text" text="2010/08"/>
						<cell bkcolor="#dfdfdf" col="7" color="#002043" display="text" text="2010/08"/>
						<cell bkcolor="#dfdfdf" col="8" color="#002043" display="text" text="2010/08"/>
						<cell bkcolor="#dfdfdf" col="9" color="#002043" display="text" text="2010/08"/>
						<cell bkcolor="#dfdfdf" col="10" color="#002043" display="text" text="2010/08"/>
						<cell bkcolor="#dfdfdf" col="11" color="#002043" display="text" text="2010/08"/>
						<cell bkcolor="#dfdfdf" col="12" color="#002043" display="text" text="2010/08"/>
						<cell bkcolor="#dfdfdf" col="13" color="#002043" display="text" text="2010/08"/>
						<cell bkcolor="#dfdfdf" col="14" color="#002043" display="text" text="2010/08"/>
					</head>
					<body>
						<cell align="center" col="0" colid="code" display="normal" suppress="1"/>
						<cell align="center" col="1" colid="col1" display="normal" suppress="2"/>
						<cell align="right" autosizing="none" col="2" colid="col2" display="normal" edit="normal"/>
						<cell align="right" autosizing="none" col="3" colid="col3" display="normal"/>
						<cell align="right" autosizing="none" col="4" colid="col4" display="normal"/>
						<cell align="right" autosizing="none" col="5" colid="col5" display="normal"/>
						<cell align="right" autosizing="none" col="6" colid="col6" display="normal" edit="normal"/>
						<cell align="right" autosizing="none" col="7" colid="col7" display="normal" edit="normal"/>
						<cell align="right" autosizing="none" col="8" colid="col8" display="normal" edit="normal"/>
						<cell align="right" autosizing="none" col="9" colid="col9" display="normal" edit="normal"/>
						<cell align="right" autosizing="none" col="10" colid="col10" display="normal" edit="normal"/>
						<cell align="right" autosizing="none" col="11" colid="col11" display="normal" edit="normal"/>
						<cell align="right" autosizing="none" col="12" colid="col12" display="normal" edit="normal"/>
						<cell align="right" autosizing="none" col="13" colid="col13" display="normal" edit="normal"/>
						<cell align="right" autosizing="none" col="14" colid="col2" display="normal" edit="normal"/>
					</body>
				</format>
			</contents>
		</Grid>
		<MaskEdit Border="Flat" BorderColor="SCROLLBAR" Color="#333333" Height="21" Id="MaskEdit0" Left="370" Mask="ZZ" MaxLength="14" TabOrder="10" Top="34" Type="STRING" Width="24"></MaskEdit>
		<Static BKColor="white" Border="Flat" BorderColor="#b4b4b4" Height="25" Id="Static2" Left="-1" TabOrder="17" Top="56" Width="1060"></Static>
		<Static BKColor="#dfdfdf" Border="Flat" BorderColor="#b4b4b4" Height="25" Id="Static3" Left="263" TabOrder="16" Top="56" Width="106"></Static>
		<Static Border="None" Color="#333333" Font="굴림,9,Bold" Height="16" Id="Static7" Left="285" Style="static" TabOrder="12" Text="거래선" Top="61" VAlign="Middle" Width="69"></Static>
		<Static BKColor="#dfdfdf" Border="Flat" BorderColor="#b4b4b4" Height="25" Id="Static8" Left="-1" TabOrder="15" Top="56" Width="106"></Static>
		<Shape BKColor="#888888" Bottom="71" Height="5" Id="Shape0" Left="275" LineColor="#dceaf7" Right="280" TabOrder="11" Top="66" Type="Ellipse" Width="5"></Shape>
		<Shape BKColor="#888888" Bottom="70" Height="5" Id="Shape2" Left="11" LineColor="#dceaf7" Right="16" TabOrder="13" Top="65" Type="Ellipse" Width="5"></Shape>
		<Static Border="None" Color="#333333" Font="굴림,9,Bold" Height="16" Id="Static9" Left="21" Style="static" TabOrder="14" Text="년월일" Top="61" VAlign="Middle" Width="69"></Static>
		<MaskEdit Border="Flat" BorderColor="SCROLLBAR" Color="#333333" Height="21" Id="MaskEdit1" Left="370" Mask="@@@@" MaxLength="14" TabOrder="18" Top="58" Type="STRING" Value="0000" Width="46"></MaskEdit>
		<MaskEdit Border="Flat" BorderColor="SCROLLBAR" Color="#333333" Height="21" Id="MaskEdit2" Left="107" Mask="@@@@/@@" MaxLength="14" TabOrder="19" Top="58" Type="STRING" Value="201008" Width="53"></MaskEdit>
		<Static Height="13" Id="Static10" Left="168" TabOrder="20" Text="~&#32;12개월" Top="63" Width="80"></Static>
		<MaskEdit Border="Flat" BorderColor="SCROLLBAR" Color="#333333" Height="21" Id="MaskEdit3" Left="434" Mask="@@@@" MaxLength="14" TabOrder="21" Top="58" Type="STRING" Value="9999" Width="46"></MaskEdit>
		<Static Height="13" Id="Static11" Left="420" TabOrder="22" Text="~" Top="63" Width="8"></Static>
		<Static BKColor="#dfdfdf" Border="Flat" BorderColor="#b4b4b4" Height="25" Id="Static12" Left="483" TabOrder="25" Top="56" Width="106"></Static>
		<Static Border="None" Color="#333333" Font="굴림,9,Bold" Height="16" Id="Static13" Left="505" Style="static" TabOrder="24" Text="계획구분" Top="61" VAlign="Middle" Width="69"></Static>
		<Shape BKColor="#888888" Bottom="71" Height="5" Id="Shape4" Left="495" LineColor="#dceaf7" Right="500" TabOrder="23" Top="66" Type="Ellipse" Width="5"></Shape>
		<MaskEdit Border="Flat" BorderColor="SCROLLBAR" Color="#333333" Height="21" Id="MaskEdit4" Left="590" MaxLength="14" TabOrder="26" Top="58" Value="1" Width="24"></MaskEdit>
		<Static Height="13" Id="Static14" Left="627" TabOrder="27" Text="(1:기본&#32;&#32;&#32;2:수정계획)" Top="62" Width="152"></Static>
		<Image FillType="STRETCH" Font="돋움,9,Bold" Height="28" Id="titleBar" ImageID="main_tit_bak" Left="-2" TabOrder="28" Width="1060"></Image>
		<Static Color="#333333" Font="돋움,9,Bold" Height="13" Id="title_text" Left="16" TabOrder="28" Top="8" Width="1032"></Static>
	</Form>
	<Script><![CDATA[#include "script::lib_script_common.js";

function onLoadCompleted(obj)
{
	getTitle();
}

function Button0_OnClick(obj)
{
	dialog("Group1::MSTZ100FMP.xml", 800, 600);
}
]]></Script>
</Window>