<?xml version="1.0" encoding="utf-8"?>
<Window>
	<Form Height="535" Id="form" Left="8" OnKeyDown="fnc_OnKeyDown" OnLoadCompleted="form_OnLoadCompleted" PidAttrib="7" Title="autoConvert" TooltipFont="Default,0" Top="8" Ver="1.0" Width="800" WorkArea="true">
		<Datasets>
			<Dataset DataSetType="Dataset" Id="ds_main"></Dataset>
			<Dataset DataSetType="Dataset" Id="ds_list"></Dataset>
		</Datasets>
		<Static Height="20" Id="ID05002" Left="20" TabOrder="0" Text="&#32;코드　　코　드　내　용&#32;&#32;&#32;&#32;코드　　코　드　내　용&#32;&#32;&#32;&#32;코드　　코　드　내　용&#32;&#32;&#32;" Top="105" Visible="FALSE" Width="780"></Static>
		<Grid AutoEnter="TRUE" AutoFit="TRUE" AutoScrollBar="None" BindDataset="ds_column" BkColor2="default" BoldHead="true" Border="Flat" BorderColor="#b4b4b4" Bottom="83" CellMoving="TRUE" ColSizing="TRUE" Editable="TRUE" Enable="true" EndLineColor="default" FillArea="TRUE" HeadBorder="Flat" HeadHeight="25" Height="27" Id="MainGrid" InputPanel="FALSE" LineColor="#b4b4b4" MinWidth="100" OnKeyDown="fnc_OnKeyDown" Right="798" TabOrder="2" TabStop="true" Top="56" UseDBuff="true" UsePopupMenu="true" UseSelColor="FALSE" Visible="true" VLineColor="#b4b4b4" WheelScrollRow="1" Width="798">
			<contents>
				<format id="Default">
					<columns>
						<col width="132"/>
						<col width="132"/>
						<col width="132"/>
						<col width="132"/>
						<col width="132"/>
						<col width="132"/>
					</columns>
					<head>
						<cell bkcolor="#dfdfdf" col="0" color="#002043" display="text" text="코드　　"/>
						<cell bkcolor="#dfdfdf" col="1" color="#002043" display="text" text="코　드　내　용"/>
						<cell bkcolor="#dfdfdf" col="2" color="#002043" display="text" text="코드　　"/>
						<cell bkcolor="#dfdfdf" col="3" color="#002043" display="text" text="코　드　내　용"/>
						<cell bkcolor="#dfdfdf" col="4" color="#002043" display="text" text="코드　　"/>
						<cell bkcolor="#dfdfdf" col="5" color="#002043" display="text" text="코　드　내　용"/>
					</head>
					<body>
						<cell align="left" col="0" colid="COLUMN_01" display="normal"/>
						<cell align="left" col="1" colid="COLUMN_02" display="normal"/>
						<cell align="left" col="2" colid="COLUMN_03" display="normal"/>
						<cell align="left" col="3" colid="COLUMN_04" display="normal"/>
						<cell align="left" col="4" colid="COLUMN_05" display="normal"/>
						<cell align="left" col="5" colid="COLUMN_06" display="normal"/>
					</body>
				</format>
			</contents>
		</Grid>
		<Static BKColor="white" Border="Flat" BorderColor="#b4b4b4" Height="25" Id="searchBar" TabOrder="16" Top="29" Width="798"></Static>
		<Image FillType="STRETCH" Height="28" Id="Image0" ImageID="main_tit_bak" TabOrder="11" Width="798"></Image>
		<Static Height="12" Id="ID01002" Left="507" TabOrder="3" Text="FHDZ070FM" Top="8" Width="90"></Static>
		<Static Height="12" Id="ID01070" Left="635" TabOrder="4" Text="2010/11/02" Top="8" Width="68"></Static>
		<Static Height="12" Id="ID02072" Left="712" TabOrder="5" Text="13:45:29" Top="8" Width="72"></Static>
		<Static Height="16" Id="ID03017" Left="392" TabOrder="6" Text="&#32;이후&#32;" Top="35" Width="36"></Static>
		<Edit AutoSelect="TRUE" Border="Flat" BorderColor="#b4b4b4" Height="21" Id="FD01013" Left="107" OnKeyDown="fnc_OnKeyDown" TabOrder="7" Top="31" Width="20"></Edit>
		<Edit AutoSelect="TRUE" Border="Flat" BorderColor="#b4b4b4" Height="20" Id="FD03014" Left="371" OnKeyDown="fnc_OnKeyDown" TabOrder="8" Top="31" Width="20"></Edit>
		<Image Height="28" Id="Image2" ImageID="main_tit_icon" Left="1" TabOrder="10" Width="29"></Image>
		<Static Color="#333333" Font="돋움,9,Bold" Height="13" Id="ID01028" Left="32" TabOrder="9" Text="생산&#32;잔업코드&#32;등록" Top="8" Width="500"></Static>
		<Static BKColor="#dfdfdf" Border="Flat" BorderColor="#b4b4b4" Height="25" Id="Static6" Left="264" TabOrder="15" Top="29" Width="106"></Static>
		<Static BKColor="#dfdfdf" Border="Flat" BorderColor="#b4b4b4" Height="25" Id="Static1" TabOrder="14" Top="29" Width="106"></Static>
		<Shape BKColor="#888888" Bottom="44" Height="5" Id="Shape3" Left="276" LineColor="#dceaf7" Right="281" TabOrder="12" Top="39" Type="Ellipse" Width="5"></Shape>
		<Shape BKColor="#888888" Bottom="43" Height="5" Id="Shape1" Left="13" LineColor="#dceaf7" Right="18" TabOrder="13" Top="38" Type="Ellipse" Width="5"></Shape>
		<Static Height="12" Id="ID03002" Left="284" TabOrder="17" Text="&#32;잔업코드&#32;:" Top="36" Width="70"></Static>
		<Static Height="12" Id="ID02002" Left="20" TabOrder="18" Text="&#32;사업부&#32;&#32;&#32;:" Top="36" Width="78"></Static>
		<Button ButtonStyle="TRUE" Height="24" Id="btn_add" ImageID="2_btn" Left="744" OnClick="btn_add_OnClick" OnKeyDown="fnc_OnKeyDown" TabOrder="19" Text="Enter" Top="29" Width="53"></Button>
		<Button ButtonStyle="TRUE" Height="23" Id="Button0" ImageID="7_btn" Left="664" OnClick="ID24063_OnClick" OnKeyDown="fnc_OnKeyDown" TabOrder="22" Text="전후화면" Top="504" Width="115"></Button>
		<Button ButtonStyle="TRUE" Height="23" Id="Button1" ImageID="7_btn" Left="544" OnClick="ID24045_OnClick" OnKeyDown="fnc_OnKeyDown" TabOrder="21" Text="작업취소" Top="504" Width="115"></Button>
		<Button ButtonStyle="TRUE" Height="23" Id="Button2" ImageID="7_btn" Left="424" OnClick="ID24027_OnClick" OnKeyDown="fnc_OnKeyDown" TabOrder="20" Text="작업종료" Top="504" Width="115"></Button>
	</Form>
	<Script><![CDATA[#include "script::lib_script_common.js";
function sendColumn(){
	Max5250.SendToColumn("COLUMN_01",ds_column.getColumn(0,"COLUMN_01"),1);
	Max5250.SendToColumn("COLUMN_02",ds_column.getColumn(0,"COLUMN_02"),1);
	Max5250.SendToColumn("COLUMN_03",ds_column.getColumn(0,"COLUMN_03"),1);
	Max5250.SendToColumn("COLUMN_04",ds_column.getColumn(0,"COLUMN_04"),1);
	Max5250.SendToColumn("COLUMN_05",ds_column.getColumn(0,"COLUMN_05"),1);
	Max5250.SendToColumn("COLUMN_06",ds_column.getColumn(0,"COLUMN_06"),1);
}
function sendField(){
	MAX5250.SendToField("FD01013",FD01013.Text );
	MAX5250.SendToField("FD03014",FD03014.Text );
	MAX5250.SendKeys("[Enter]");
}
function form_OnLoadCompleted(obj)
{
	form.SetFocus();
	var subStr = "";
	var sKind		= "CONVERTXMLDATA";	
	var sMethodName = "service::max5250/convertxmlData.do"; 
	var sInDataSet  = ""; 	
	var sOutDataSet = "ds_main=ds_main"; 	
	var mainStr = max5250.GetScreenData(1,24); 	
	var arg			= " str=" + quote(mainStr); 	
	Transaction(sKind, sMethodName, sInDataSet, sOutDataSet, arg, "fnc_callBack"); 	
}
function fnc_callBack(svcId,rntCode, errCode, errMsg){
	if(svcId=="CONVERTXMLDATA"){
	ID01002.Text=ds_main.getColumn(0,"ID01002");
		ID01002.Color=ds_main.getColumn(0,"ID01002_c");
		ID01002.BkColor=ds_main.getColumn(0,"ID01002_b");
		ID01002.Font=ds_main.getColumn(0,"ID01002_f");
		ID01028.Text=ds_main.getColumn(0,"ID01028");
		ID01028.Color=ds_main.getColumn(0,"ID01028_c");
		ID01028.BkColor=ds_main.getColumn(0,"ID01028_b");
		ID01028.Font=ds_main.getColumn(0,"ID01028_f");
		ID01070.Text=ds_main.getColumn(0,"ID01070");
		ID01070.Color=ds_main.getColumn(0,"ID01070_c");
		ID01070.BkColor=ds_main.getColumn(0,"ID01070_b");
		ID01070.Font=ds_main.getColumn(0,"ID01070_f");
		ID02002.Text=ds_main.getColumn(0,"ID02002");
		ID02002.Color=ds_main.getColumn(0,"ID02002_c");
		ID02002.BkColor=ds_main.getColumn(0,"ID02002_b");
		ID02002.Font=ds_main.getColumn(0,"ID02002_f");
		
		ID02072.Text=ds_main.getColumn(0,"ID02072");
		ID02072.Color=ds_main.getColumn(0,"ID02072_c");
		ID02072.BkColor=ds_main.getColumn(0,"ID02072_b");
		ID02072.Font=ds_main.getColumn(0,"ID02072_f");
		ID03002.Text=ds_main.getColumn(0,"ID03002");
		ID03002.Color=ds_main.getColumn(0,"ID03002_c");
		ID03002.BkColor=ds_main.getColumn(0,"ID03002_b");
		ID03002.Font=ds_main.getColumn(0,"ID03002_f");
		ID03017.Text=ds_main.getColumn(0,"ID03017");
		ID03017.Color=ds_main.getColumn(0,"ID03017_c");
		ID03017.BkColor=ds_main.getColumn(0,"ID03017_b");
		ID03017.Font=ds_main.getColumn(0,"ID03017_f");
		
		
		FD01013.Text=ds_main.getColumn(0,"ID02014");
		FD01013.Color=ds_main.getColumn(0,"FD01013_c");
		FD01013.BkColor=ds_main.getColumn(0,"FD01013_b");
		FD01013.Font=ds_main.getColumn(0,"FD01013_f");
		FD01013.Enable=ds_main.getColumn(0,"FD01013_s");
		FD03014.Text=ds_main.getColumn(0,"FD03014");
		FD03014.Color=ds_main.getColumn(0,"FD03014_c");
		FD03014.BkColor=ds_main.getColumn(0,"FD03014_b");
		FD03014.Font=ds_main.getColumn(0,"FD03014_f");
		FD03014.Enable=ds_main.getColumn(0,"FD03014_s");
	}
}

function fnc_OnKeyDown(obj,nChar,bShift,bCtrl, bAlt,LLParam,HLParam){
	if(nChar == 13){
		sendColumn();
		sendField();
	}
}

function btn_add_OnClick(obj)
{
	initScreenName = "FHDZ070FM_1";
	sendField();
}

function ID24027_OnClick(obj)
{
	MAX5250.SendKeys("[PF03]");
}
]]></Script>
</Window>